Metadata-Version: 2.1
Name: strings-oc
Version: 1.0.6
Summary: Generic functions for dealing with and generating strings
Home-page: https://ouroboroscoding.com/strings/
Author: Chris Nasr - Ouroboros Coding Inc.
Author-email: chris@ouroboroscoding.com
License: MIT
Project-URL: Documentation, https://ouroboroscoding.com/strings/
Project-URL: Source, https://github.com/ouroboroscoding/strings-python
Project-URL: Tracker, https://github.com/ouroboroscoding/strings-python/issues
Keywords: strings,string manipulation,string generation
Platform: UNKNOWN
Requires-Python: >=3.10
License-File: LICENSE
